<?xml version="1.0" encoding="utf-8" ?>
<XnaContent>
    <Asset Type="DataTypes.MusicManiaSong">
        <Name>Stars and boxes</Name>
        <Tempo>108.0</Tempo>
        <StartsAt>0.035</StartsAt>
        <Arrows>
            <Item>
                <Time>2.22</Time>
                <Direction>D</Direction>
            </Item>
            <Item>
                <Time>3.88</Time>
                <Direction>L</Direction>
            </Item>
            <Item>
                <Time>4.15</Time>
                <Direction>L</Direction>
            </Item>
            <Item>
                <Time>4.44</Time>
                <Direction>L</Direction>
            </Item>
            <Item>
                <Time>6.11</Time>
                <Direction>R</Direction>
            </Item>
            <Item>
                <Time>6.38</Time>
                <Direction>R</Direction>
            </Item>
            <Item>
                <Time>6.66</Time>
                <Direction>R</Direction>
            </Item>
            <Item>
                <Time>8.33</Time>
                <Direction>D</Direction>
            </Item>
            <Item>
                <Time>8.61</Time>
                <Direction>D</Direction>
            </Item>
            <Item>
                <Time>8.88</Time>
                <Direction>D</Direction>
            </Item>
            <Item>
                <Time>10.00</Time>
                <Direction>U</Direction>
            </Item>
            <Item>
                <Time>10.27</Time>
                <Direction>U</Direction>
            </Item>
            <Item>
                <Time>10.55</Time>
                <Direction>U</Direction>
            </Item>
            <Item>
                <Time>11.11</Time>
                <Direction>U</Direction>
            </Item>
            <Item>
                <Time>11.66</Time>
                <Direction>U</Direction>
            </Item>
            <Item>
                <Time>12.22</Time>
                <Direction>L</Direction>
            </Item>
            <Item>
                <Time>12.77</Time>
                <Direction>L</Direction>
            </Item>
            <Item>
                <Time>13.33</Time>
                <Direction>R</Direction>
            </Item>
            <Item>
                <Time>13.88</Time>
                <Direction>R</Direction>
            </Item>
            <Item>
                <Time>14.44</Time>
                <Direction>D</Direction>
            </Item>
            <Item>
                <Time>15.00</Time>
                <Direction>D</Direction>
            </Item>
            <Item>
                <Time>15.55</Time>
                <Direction>U</Direction>
            </Item>
            <Item>
                <Time>16.11</Time>
                <Direction>D</Direction>
            </Item>
            <Item>
                <Time>16.66</Time>
                <Direction>L</Direction>
            </Item>
            <Item>
                <Time>17.22</Time>
                <Direction>R</Direction>
            </Item>
            <Item>
                <Time>17.77</Time>
                <Direction>D</Direction>
            </Item>
            <Item>
                <Time>18.88</Time>
                <Direction>L</Direction>
            </Item>
            <Item>
                <Time>19.16</Time>
                <Direction>L</Direction>
            </Item>
            <Item>
                <Time>19.44</Time>
                <Direction>L</Direction>
            </Item>
            <Item>
                <Time>20.55</Time>
                <Direction>U</Direction>
            </Item>
            <Item>
                <Time>21.11</Time>
                <Direction>L</Direction>
            </Item>
            <Item>
                <Time>21.66</Time>
                <Direction>L</Direction>
            </Item>
            <Item>
                <Time>22.77</Time>
                <Direction>D</Direction>
            </Item>
            <Item>
                <Time>23.33</Time>
                <Direction>R</Direction>
            </Item>
            <Item>
                <Time>23.88</Time>
                <Direction>R</Direction>
            </Item>
            <Item>
                <Time>24.44</Time>
                <Direction>L</Direction>
            </Item>
            <Item>
                <Time>25.00</Time>
                <Direction>R</Direction>
            </Item>
            <Item>
                <Time>25.55</Time>
                <Direction>L</Direction>
            </Item>
            <Item>
                <Time>26.11</Time>
                <Direction>R</Direction>
            </Item>
            <Item>
                <Time>26.66</Time>
                <Direction>D</Direction>
            </Item>
            <Item>
                <Time>27.22</Time>
                <Direction>U</Direction>
            </Item>
            <Item>
                <Time>27.77</Time>
                <Direction>L</Direction>
            </Item>
            <Item>
                <Time>28.05</Time>
                <Direction>L</Direction>
            </Item>
            <Item>
                <Time>28.33</Time>
                <Direction>L</Direction>
            </Item>
            <Item>
                <Time>29.44</Time>
                <Direction>U</Direction>
            </Item>
            <Item>
                <Time>30.00</Time>
                <Direction>D</Direction>
            </Item>
            <Item>
                <Time>30.55</Time>
                <Direction>D</Direction>
            </Item>
            <Item>
                <Time>31.66</Time>
                <Direction>L</Direction>
            </Item>
            <Item>
                <Time>32.22</Time>
                <Direction>R</Direction>
            </Item>
            <Item>
                <Time>32.77</Time>
                <Direction>R</Direction>
            </Item>
            <Item>
                <Time>33.33</Time>
                <Direction>D</Direction>
            </Item>
            <Item>
                <Time>33.88</Time>
                <Direction>R</Direction>
            </Item>
            <Item>
                <Time>34.44</Time>
                <Direction>U</Direction>
            </Item>
            <Item>
                <Time>35.00</Time>
                <Direction>L</Direction>
            </Item>
            <Item>
                <Time>35.55</Time>
                <Direction>D</Direction>
            </Item>
            <Item>
                <Time>36.66</Time>
                <Direction>D</Direction>
            </Item>
            <Item>
                <Time>36.94</Time>
                <Direction>U</Direction>
            </Item>
            <Item>
                <Time>37.22</Time>
                <Direction>U</Direction>
            </Item>
            <Item>
                <Time>37.77</Time>
                <Direction>R</Direction>
            </Item>
            <Item>
                <Time>38.88</Time>
                <Direction>L</Direction>
            </Item>
            <Item>
                <Time>39.44</Time>
                <Direction>U</Direction>
            </Item>
            <Item>
                <Time>39.72</Time>
                <Direction>U</Direction>
            </Item>
            <Item>
                <Time>40.00</Time>
                <Direction>D</Direction>
            </Item>
            <Item>
                <Time>40.55</Time>
                <Direction>L</Direction>
            </Item>
            <Item>
                <Time>41.11</Time>
                <Direction>D</Direction>
            </Item>
            <Item>
                <Time>41.66</Time>
                <Direction>U</Direction>
            </Item>
            <Item>
                <Time>41.94</Time>
                <Direction>U</Direction>
            </Item>
            <Item>
                <Time>42.22</Time>
                <Direction>D</Direction>
            </Item>
            <Item>
                <Time>43.33</Time>
                <Direction>D</Direction>
            </Item>
            <Item>
                <Time>43.88</Time>
                <Direction>R</Direction>
            </Item>
            <Item>
                <Time>44.16</Time>
                <Direction>R</Direction>
            </Item>
            <Item>
                <Time>44.44</Time>
                <Direction>L</Direction>
            </Item>
            <Item>
                <Time>45.00</Time>
                <Direction>R</Direction>
            </Item>
            <Item>
                <Time>45.83</Time>
                <Direction>D</Direction>
            </Item>
            <Item>
                <Time>46.11</Time>
                <Direction>U</Direction>
            </Item>
            <Item>
                <Time>46.66</Time>
                <Direction>L</Direction>
            </Item>
            <Item>
                <Time>47.22</Time>
                <Direction>L</Direction>
            </Item>
            <Item>
                <Time>47.77</Time>
                <Direction>R</Direction>
            </Item>
            <Item>
                <Time>48.33</Time>
                <Direction>R</Direction>
            </Item>
            <Item>
                <Time>48.88</Time>
                <Direction>D</Direction>
            </Item>
            <Item>
                <Time>49.44</Time>
                <Direction>U</Direction>
            </Item>
            <Item>
                <Time>50.00</Time>
                <Direction>L</Direction>
            </Item>
            <Item>
                <Time>50.55</Time>
                <Direction>R</Direction>
            </Item>
            <Item>
                <Time>51.11</Time>
                <Direction>D</Direction>
            </Item>
            <Item>
                <Time>52.22</Time>
                <Direction>R</Direction>
            </Item>
            <Item>
                <Time>52.50</Time>
                <Direction>R</Direction>
            </Item>
            <Item>
                <Time>52.77</Time>
                <Direction>R</Direction>
            </Item>
            <Item>
                <Time>53.33</Time>
                <Direction>D</Direction>
            </Item>
            <Item>
                <Time>54.02</Time>
                <Direction>U</Direction>
            </Item>
            <Item>
                <Time>54.44</Time>
                <Direction>L</Direction>
            </Item>
            <Item>
                <Time>54.72</Time>
                <Direction>U</Direction>
            </Item>
            <Item>
                <Time>55.00</Time>
                <Direction>U</Direction>
            </Item>
        </Arrows>
    </Asset>
</XnaContent>